pyublox/__init__.py
pyublox/commands.py
pyublox/main.py
pyublox/ublox/__init__.py
pyublox/ublox/config.py
pyublox/ublox/constants.py
pyublox/ublox/core.py
pyublox/ublox/helpers.py
pyublox/ublox/receiver.py
pyublox-3.1.4.dist-info/LICENSE
pyublox-3.1.4.dist-info/METADATA
pyublox-3.1.4.dist-info/WHEEL
pyublox-3.1.4.dist-info/entry_points.txt
pyublox-3.1.4.dist-info/top_level.txt
pyublox-3.1.4.dist-info/RECORD
