Metadata-Version: 2.1
Name: pyublox
Version: 3.1.4
Summary: Interface with ublox chipsets using Python.
Home-page: https://gitlab.esa.int/AMIC/pyublox.git
Author: Rokubun
Author-email: info@rokubun.cat
License: EUROPEAN SPACE AGENCY PUBLIC LICENSE - V2.4 - STRONG COPYLEFT
Platform: UNKNOWN
